arro3.libs/libgcc_s-39080030.so.1
arro3/compute/__init__.py
arro3/compute/_aggregate.pyi
arro3/compute/_arith.pyi
arro3/compute/_boolean.pyi
arro3/compute/_cast.pyi
arro3/compute/_compute.cpython-310-aarch64-linux-gnu.so
arro3/compute/_compute.pyi
arro3/compute/_dictionary.pyi
arro3/compute/_filter.pyi
arro3/compute/_take.pyi
arro3/compute/_temporal.pyi
arro3/compute/enums.py
arro3/compute/py.typed
arro3/compute/types.py
arro3_compute-0.6.4.dist-info/METADATA
arro3_compute-0.6.4.dist-info/WHEEL
arro3_compute-0.6.4.dist-info/RECORD
